cooldevcode/__init__.py
cooldevcode/cooldevcode.py
cooldevcode-0.0.1.dist-info/METADATA
cooldevcode-0.0.1.dist-info/WHEEL
cooldevcode-0.0.1.dist-info/top_level.txt
cooldevcode-0.0.1.dist-info/RECORD
