Metadata-Version: 2.1
Name: cooldevcode
Version: 0.0.1
Summary: CoolDevcode Version 0.0.1
Home-page: UNKNOWN
Author: YeaeThawe
Author-email: <yeaethawe@gmail.com>
License: UNKNOWN
Keywords: python
Platform: UNKNOWN
Classifier: Development Status :: 1 - Planning
Classifier: Intended Audience :: Developers
Classifier: Programming Language :: Python :: 3
Classifier: Operating System :: Unix
Classifier: Operating System :: MacOS :: MacOS X
Classifier: Operating System :: Microsoft :: Windows
Requires-Dist: tkinter
Requires-Dist: string
